objaverse_xl/__init__.py
objaverse_xl/abstract.py
objaverse_xl/github.py
objaverse_xl/objaverse_downloader.py
objaverse_xl/sketchfab.py
objaverse_xl/smithsonian.py
objaverse_xl/thingiverse.py
objaverse_xl/utils.py
objaverse_xl-0.1.3.dist-info/LICENSE
objaverse_xl-0.1.3.dist-info/METADATA
objaverse_xl-0.1.3.dist-info/WHEEL
objaverse_xl-0.1.3.dist-info/top_level.txt
objaverse_xl-0.1.3.dist-info/RECORD
