Metadata-Version: 2.1
Name: objaverse-xl
Version: 0.1.3
Summary: Objaverse-XL is an open dataset of over 10 million 3D objects
Home-page: https://huggingface.co/datasets/allenai/objaverse-xl
Author: Allen Institute for AI
Author-email: mattd@allenai.org
License: UNKNOWN
Platform: UNKNOWN
Classifier: Programming Language :: Python :: 3
Classifier: License :: OSI Approved :: Apache Software License
Requires-Dist: requests
Requires-Dist: pandas
Requires-Dist: pyarrow
Requires-Dist: tqdm
Requires-Dist: loguru
Requires-Dist: fsspec >=2022.11.0
Requires-Dist: gputil ==1.4.0
Provides-Extra: s3
Requires-Dist: s3fs ==0.4.2 ; extra == 's3'
